saxonche-stubs/__init__.pyi
saxonche_stubs-0.7.2.dist-info/METADATA
saxonche_stubs-0.7.2.dist-info/WHEEL
saxonche_stubs-0.7.2.dist-info/RECORD
